pykn_mysqltools/__init__.py
pykn_mysqltools/utilities.py
pykn_mysqltools-0.0.6.dist-info/METADATA
pykn_mysqltools-0.0.6.dist-info/WHEEL
pykn_mysqltools-0.0.6.dist-info/licenses/LICENSE
pykn_mysqltools-0.0.6.dist-info/RECORD
