Metadata-Version: 2.1
Name: pykn_mysqltools
Version: 0.0.6
Summary: Utilities for interacting with MySQL and CSVs.
Project-URL: Homepage, https://github.com/knorquist/pykn_mysqltools
Project-URL: Bug tracker, https://github.com/knorquist/pykn_mysqltools/issues
Author-email: Kylie Norquist <kylie.norquist@newbit.dev>
License-File: LICENSE
Classifier: License :: OSI Approved :: MIT License
Classifier: Operating System :: OS Independent
Classifier: Programming Language :: Python :: 3
Requires-Python: >=3.10
